{
  "info": {
    "year": 2023,
    "version": "0",
    "description": "Generated by FathomNet",
    "contributor": "FathomNet",
    "url": "https://fathomnet.org",
    "date_created": "2023/04/22"
  },
  "images": [
    {
      "id": 1,
      "width": 1920,
      "height": 1080,
      "file_name": "8345f744-63df-44f5-bece-9c2ef1403ee2.png",
      "license": 0,
      "flickr_url": "https://fathomnet.org/static/m3/framegrabs/Doc%20Ricketts/images/0230/05_51_36_15.png",
      "coco_url": "https://fathomnet.org/static/m3/framegrabs/Doc%20Ricketts/images/0230/05_51_36_15.png",
      "date_captured": null
    },
    {
      "id": 2,
      "width": 714,
      "height": 368,
      "file_name": "21bd3b31-3d2d-4416-9473-e7470c357065.png",
      "license": 0,
      "flickr_url": "https://fathomnet.org/static/m3/framegrabs/Doc%20Ricketts/images/0339/02_25_18_10.png",
      "coco_url": "https://fathomnet.org/static/m3/framegrabs/Doc%20Ricketts/images/0339/02_25_18_10.png",
      "date_captured": null
    }
  ],
  "licenses": [
    {
      "id": 0,
      "name": "FathomNet",
      "url": "http://fathomnet.org/fathomnet/#/license"
    }
  ],
  "annotations": [
    {
      "id": 1,
      "image_id": 1,
      "category_id": 3,
      "segmentation": [],
      "area": 28014.0,
      "bbox": [
        311.0,
        533.0,
        203.0,
        138.0
      ],
      "iscrowd": 0
    },
    {
      "id": 2,
      "image_id": 1,
      "category_id": 2,
      "segmentation": [],
      "area": 32800.0,
      "bbox": [
        230.0,
        148.0,
        160.0,
        205.0
      ],
      "iscrowd": 0
    },
    {
      "id": 3,
      "image_id": 1,
      "category_id": 1,
      "segmentation": [],
      "area": 5150.0,
      "bbox": [
        792.0,
        457.0,
        103.0,
        50.0
      ],
      "iscrowd": 0
    },
    {
      "id": 4,
      "image_id": 2,
      "category_id": 2,
      "segmentation": [],
      "area": 3640.0,
      "bbox": [
        96.0,
        47.0,
        52.0,
        70.0
      ],
      "iscrowd": 0
    }
  ],
  "categories": [
    {
      "id": 1,
      "name": "Ophiuroidea",
      "supercategory": ""
    },
    {
      "id": 2,
      "name": "Peniagone",
      "supercategory": ""
    },
    {
      "id": 3,
      "name": "Synallactidae gen. et sp. indet.",
      "supercategory": ""
    }
  ]
}